pyblog
