Metadata-Version: 1.0
Name: pyblog
Version: 0.6.3
Summary: Lightweight python static blog generator
Home-page: http://github.com/cesarparent/pyblog
Author: Cesar Parent
Author-email: cesar@cesarparent.com
License: MIT
Platform: UNKNOWN
